README.rst
setup.py
django_skin.egg-info/PKG-INFO
django_skin.egg-info/SOURCES.txt
django_skin.egg-info/dependency_links.txt
django_skin.egg-info/requires.txt
django_skin.egg-info/top_level.txt
skin/__init__.py
skin/admin.py
skin/conf.py
skin/models.py
skin/migrations/0001_initial.py
skin/migrations/__init__.py
skin/south_migrations/0001_initial.py
skin/south_migrations/__init__.py
skin/template/__init__.py
skin/template/loaders/__init__.py
skin/template/loaders/app_directories.py
skin/template/loaders/filesystem.py
skin/template/loaders/util.py
skin/views/__init__.py
skin/views/views.py
tests/__init__.py
tests/manage.py
tests/settings.py
tests/urls.py
tests/template_loader/__init__.py
tests/template_loader/tests.py