Metadata-Version: 1.1
Name: django-skin
Version: 0.1.2
Summary: Add template skins to django.
Home-page: https://github.com/dwatkinsweb/django-skin
Author: David Watkins
Author-email: dwatkinsweb@gmail.com
License: MIT
Platform: any
Classifier: Environment :: Web Environment
Classifier: Framework :: Django
Classifier: Intended Audience :: Developers
Classifier: License :: OSI Approved :: MIT License
Classifier: Operating System :: OS Independent
Classifier: Programming Language :: Python :: 2.7
Classifier: Topic :: Internet :: WWW/HTTP :: Dynamic Content
Classifier: Topic :: Software Development :: Libraries :: Python Modules
